MANIFEST.in
README.md
setup.py
finsym/__init__.py
finsym/serialize2.py
finsym/serialize3.py
finsym/symbols.py
finsym/util.py
finsym/version.py
finsym.egg-info/PKG-INFO
finsym.egg-info/SOURCES.txt
finsym.egg-info/dependency_links.txt
finsym.egg-info/requires.txt
finsym.egg-info/top_level.txt