Metadata-Version: 1.1
Name: finsym
Version: 0.0.2
Summary: Package for representing financial symbols
Home-page: https://github.com/aabdullah-bos/finsym
Author: Aquil H. Abdullah
Author-email: aquil.abdullah@lgmail.com
License: UNKNOWN
Download-URL: https://github.com/aabdullah-bos/finsymarchive/0.0.2.tar.gz
Platform: UNKNOWN
